cybermarket_client/__init__.py
cybermarket_client/__main__.py
cybermarket_client/lang.py
cybermarket_client/logic.py
cybermarket_client/logo.ico
cybermarket_client/request.py
cybermarket_client/settings.py
cybermarket_client/ui.py
cybermarket_client/locale/ru_RU/LC_MESSAGES/Russian.mo
cybermarket_client/locale/zh_CN/LC_MESSAGES/Chinese.mo
cybermarket_client/static/index.ui
cybermarket_client/static/logo.png
cybermarket_client/static/merchant_index.ui
cybermarket_client/static/merchant_login.ui
cybermarket_client/static/merchant_register.ui
cybermarket_client/static/user_login.ui
cybermarket_client/static/user_register.ui
cybermarket_client/static/user_shopping_cart.ui
cybermarket_client/static/user_update.ui
cybermarket_client-1.0.0.dist-info/LICENSE
cybermarket_client-1.0.0.dist-info/METADATA
cybermarket_client-1.0.0.dist-info/WHEEL
cybermarket_client-1.0.0.dist-info/top_level.txt
cybermarket_client-1.0.0.dist-info/RECORD
