Metadata-Version: 2.1
Name: cybermarket_client
Version: 1.0.0
Summary: A client that simulates a supermarket, has a visual user and merchant interface, allowing customers to purchase goods and merchants to manage goods.
Author-email: Qi Tang <t390697002@gmail.com>
License: MIT License
Keywords: shopping,online-market
Classifier: Programming Language :: Python :: 3
Requires-Python: >=3.10
License-File: LICENSE
Requires-Dist: pandas ==2.2.1
Requires-Dist: PyQt5 ==5.15.9
Requires-Dist: loguru ==0.6.0
Requires-Dist: python-dotenv ==0.21.0
Requires-Dist: click ==8.1.7
